jupyterlab_a11y_checker/__init__.py
jupyterlab_a11y_checker/_version.py
jupyterlab_a11y_checker/labextension/build_log.json
jupyterlab_a11y_checker/labextension/package.json
jupyterlab_a11y_checker/labextension/schemas/jupyterlab-a11y-checker/package.json.orig
jupyterlab_a11y_checker/labextension/schemas/jupyterlab-a11y-checker/plugin.json
jupyterlab_a11y_checker/labextension/static/lib_index_js.4c20aac788196d0e5883.js
jupyterlab_a11y_checker/labextension/static/lib_index_js.4c20aac788196d0e5883.js.map
jupyterlab_a11y_checker/labextension/static/remoteEntry.bbf8ea16c2bee535c509.js
jupyterlab_a11y_checker/labextension/static/remoteEntry.bbf8ea16c2bee535c509.js.map
jupyterlab_a11y_checker/labextension/static/style.js
jupyterlab_a11y_checker/labextension/static/style_index_js.334ba7eb844ddcf8cc0a.js
jupyterlab_a11y_checker/labextension/static/style_index_js.334ba7eb844ddcf8cc0a.js.map
jupyterlab_a11y_checker/labextension/static/vendors-node_modules_axe-core_axe_js.815e04f91818992167e2.js
jupyterlab_a11y_checker/labextension/static/vendors-node_modules_axe-core_axe_js.815e04f91818992167e2.js.map
jupyterlab_a11y_checker/labextension/static/vendors-node_modules_axios_index_js.4a4a50af14346a8e8cd7.js
jupyterlab_a11y_checker/labextension/static/vendors-node_modules_axios_index_js.4a4a50af14346a8e8cd7.js.map
jupyterlab_a11y_checker/labextension/static/vendors-node_modules_marked_lib_marked_esm_js.eb01d7c5217deab8dbf9.js
jupyterlab_a11y_checker/labextension/static/vendors-node_modules_marked_lib_marked_esm_js.eb01d7c5217deab8dbf9.js.map
jupyterlab_a11y_checker/labextension/static/vendors-node_modules_tesseract_js_src_index_js.f83b4ce4953ba3e1561b.js
jupyterlab_a11y_checker/labextension/static/vendors-node_modules_tesseract_js_src_index_js.f83b4ce4953ba3e1561b.js.map
jupyterlab_a11y_checker-0.2.5.data/data/share/jupyter/labextensions/jupyterlab-a11y-checker/build_log.json
jupyterlab_a11y_checker-0.2.5.data/data/share/jupyter/labextensions/jupyterlab-a11y-checker/package.json
jupyterlab_a11y_checker-0.2.5.dist-info/METADATA
jupyterlab_a11y_checker-0.2.5.dist-info/WHEEL
jupyterlab_a11y_checker-0.2.5.dist-info/licenses/LICENSE
jupyterlab_a11y_checker-0.2.5.dist-info/RECORD
