Metadata-Version: 2.4
Name: jupyterlab_a11y_checker
Version: 0.2.5
Summary: A JupyterLab extension that checks and suggests fixes for a11y issues.
Project-URL: Homepage, https://github.com/berkeley-dsep-infra/jupyterlab-a11y-checker
Project-URL: Bug Tracker, https://github.com/berkeley-dsep-infra/jupyterlab-a11y-checker/issues
Project-URL: Repository, https://github.com/berkeley-dsep-infra/jupyterlab-a11y-checker.git
Author: Chanbin Park
License: BSD 3-Clause License
License-File: LICENSE
Keywords: jupyter,jupyterlab,jupyterlab-extension
Classifier: Framework :: Jupyter
Classifier: Framework :: Jupyter :: JupyterLab
Classifier: Framework :: Jupyter :: JupyterLab :: 4
Classifier: Framework :: Jupyter :: JupyterLab :: Extensions
Classifier: Framework :: Jupyter :: JupyterLab :: Extensions :: Prebuilt
Classifier: License :: OSI Approved :: BSD License
Classifier: Programming Language :: Python
Classifier: Programming Language :: Python :: 3
Classifier: Programming Language :: Python :: 3.9
Classifier: Programming Language :: Python :: 3.10
Classifier: Programming Language :: Python :: 3.11
Classifier: Programming Language :: Python :: 3.12
Classifier: Programming Language :: Python :: 3.13
Requires-Python: >=3.9
